snow_docs/__init__.py
snow_docs/app.py
snow_docs-1.0.1.dist-info/licenses/LICENSE
snow_docs-1.0.1.dist-info/WHEEL
snow_docs-1.0.1.dist-info/entry_points.txt
snow_docs-1.0.1.dist-info/METADATA
snow_docs-1.0.1.dist-info/RECORD
